arcaflow_plugin_template_python/example_plugin.py
arcaflow_plugin_template_python-0.1.0.dist-info/LICENSE
arcaflow_plugin_template_python-0.1.0.dist-info/WHEEL
arcaflow_plugin_template_python-0.1.0.dist-info/METADATA
arcaflow_plugin_template_python-0.1.0.dist-info/RECORD
