Metadata-Version: 2.1
Name: arcaflow-plugin-template-python
Version: 0.1.0
Summary: 
License: Apache-2.0+GPL-2.0-only
Author: Arcalot
Requires-Python: >=3.9,<4.0
Classifier: License :: Other/Proprietary License
Classifier: Programming Language :: Python :: 3
Classifier: Programming Language :: Python :: 3.9
Classifier: Programming Language :: Python :: 3.10
Classifier: Programming Language :: Python :: 3.11
Requires-Dist: arcaflow-plugin-sdk (==0.9.0)
